ddmail_dmcp_keyhandler/__init__.py
ddmail_dmcp_keyhandler/application.py
ddmail_dmcp_keyhandler-0.0.2.dist-info/METADATA
ddmail_dmcp_keyhandler-0.0.2.dist-info/WHEEL
ddmail_dmcp_keyhandler-0.0.2.dist-info/licenses/LICENSE
ddmail_dmcp_keyhandler-0.0.2.dist-info/RECORD
